easy_docs/__init__.py
easy_docs/docsify.py
easy_docs/util.py
easy_docs-1.0.3.dist-info/METADATA
easy_docs-1.0.3.dist-info/WHEEL
easy_docs-1.0.3.dist-info/entry_points.txt
easy_docs-1.0.3.dist-info/top_level.txt
easy_docs-1.0.3.dist-info/RECORD
