Metadata-Version: 2.1
Name: easy-docs
Version: 1.0.3
Summary: UNKNOWN
Home-page: UNKNOWN
Author: Yaronzz
Author-email: yaronhuang@foxmail.com
License: MIT Licence
Platform: any
Requires-Dist: requests
